client/__init__.py
client/client_db.py
client/client_gui.py
client/transport.py
client/ui/__init__.py
lib/__init__.py
lib/decoration.py
lib/descryptors.py
lib/errors.py
lib/metaclasses.py
lib/utils.py
lib/variables.py
logs/__init__.py
logs/config_client_log.py
mini_chat_client-0.0.2.dist-info/METADATA
mini_chat_client-0.0.2.dist-info/WHEEL
mini_chat_client-0.0.2.dist-info/top_level.txt
mini_chat_client-0.0.2.dist-info/RECORD
